drcode_python/__init__.py
drcode_python/drcode_python.py
drcode_python-1.0.2.dist-info/METADATA
drcode_python-1.0.2.dist-info/WHEEL
drcode_python-1.0.2.dist-info/top_level.txt
drcode_python-1.0.2.dist-info/RECORD
