Metadata-Version: 2.1
Name: drcode-python
Version: 1.0.2
Summary: This package provides a comprehensive solution for integrating advanced error tracking and performance monitoring into your application. It offers a set of powerful configuration options to tailor the integration to your specific needs.
Home-page: https://github.com/airia-in/DrCode-python-package
Author: Ashutosh Renu
Author-email: ashutosh@airia.in
Project-URL: Documentation, https://github.com/airia-in/DrCode-python-package#readme
Project-URL: Source, https://github.com/airia-in/DrCode-python-package
Classifier: Programming Language :: Python :: 3
Classifier: License :: OSI Approved :: MIT License
Classifier: Operating System :: OS Independent
Classifier: Intended Audience :: Developers
Classifier: Topic :: Software Development :: Libraries :: Python Modules
Requires-Python: >=3.6
Requires-Dist: sentry-sdk >=2.0.0
